pixiv_crawler/__init__.py
pixiv_crawler/login_sim.py
pixiv_crawler/myconfig.py
pixiv_crawler/scraper_manga.py
pixiv_crawler-0.1.2.dist-info/LICENSE.txt
pixiv_crawler-0.1.2.dist-info/METADATA
pixiv_crawler-0.1.2.dist-info/WHEEL
pixiv_crawler-0.1.2.dist-info/top_level.txt
pixiv_crawler-0.1.2.dist-info/RECORD
