Metadata-Version: 2.1
Name: pixiv-crawler
Version: 0.1.2
Summary: A tool to download pixiv pictures
Home-page: https://github.com/Akaisorani/pixiv-crawler
Author: Akaisorani
Author-email: cavsolar@gmail.com
License: UNKNOWN
Platform: UNKNOWN
Classifier: Programming Language :: Python :: 3
Classifier: License :: OSI Approved :: MIT License
Classifier: Operating System :: OS Independent
Requires-Dist: requests (>=2.18.4)
Requires-Dist: selenium
